semantictool/__init__.py
semantictool/main.py
semantictool/api/__init__.py
semantictool/config/loader.py
semantictool/config/models.py
semantictool-0.0.1.dist-info/METADATA
semantictool-0.0.1.dist-info/WHEEL
semantictool-0.0.1.dist-info/entry_points.txt
semantictool-0.0.1.dist-info/RECORD
